arus_muss/__init__.py
arus_muss/classifier.py
arus_muss/cli.py
arus_muss/feature_vector.py
arus_muss/har_model.py
arus_muss/models/MUSS_HAR-ACTIVITY_VALIDATED-ALL-NDW-SPADES_LAB.har
arus_muss/models/MUSS_HAR-INTENSITY-ALL-DW_DA-SPADES_LAB.har
arus_muss/models/MUSS_HAR-INTENSITY-ALL-NDW-SPADES_LAB.har
arus_muss/models/MUSS_HAR-POSTURE_VALIDATED-ALL-NDW-SPADES_LAB.har
arus_muss/tests/__init__.py
arus_muss/tests/conftest.py
arus_muss/tests/test_feature_vector.py
arus_muss/tests/test_model.py
arus_muss-0.2.0.dist-info/entry_points.txt
arus_muss-0.2.0.dist-info/WHEEL
arus_muss-0.2.0.dist-info/METADATA
arus_muss-0.2.0.dist-info/RECORD
