Metadata-Version: 2.1
Name: arus-muss
Version: 0.2.0
Summary: Package for MUSS activity recognition algorithm (see doi: 10.1249/MSS.0000000000002306 for the description of the algorithm).
License: MIT
Author: Qu Tang
Author-email: tang.q@northeastern.edu
Requires-Python: >=3.7,<4.0
Classifier: License :: OSI Approved :: MIT License
Classifier: Programming Language :: Python :: 3
Classifier: Programming Language :: Python :: 3.7
Classifier: Programming Language :: Python :: 3.8
Requires-Dist: arus[dev] (>=1.1.18,<2.0.0)
